cisco_scc_sdk-1.0.2.dist-info/licenses/LICENSE
scc_sdk/__init__.py
scc_sdk/client.py
scc_sdk/exceptions.py
scc_sdk/resources/__init__.py
scc_sdk/resources/base.py
scc_sdk/resources/groups.py
scc_sdk/resources/organizations.py
scc_sdk/resources/roles.py
scc_sdk/resources/subscriptions.py
scc_sdk/resources/tokens.py
scc_sdk/resources/users.py
cisco_scc_sdk-1.0.2.dist-info/METADATA
cisco_scc_sdk-1.0.2.dist-info/WHEEL
cisco_scc_sdk-1.0.2.dist-info/top_level.txt
cisco_scc_sdk-1.0.2.dist-info/RECORD
